synth_graph/__init__.py
synth_graph-0.1.0.dist-info/METADATA
synth_graph-0.1.0.dist-info/WHEEL
synth_graph-0.1.0.dist-info/top_level.txt
synth_graph-0.1.0.dist-info/RECORD
