Metadata-Version: 2.4
Name: synth-graph
Version: 0.1.0
Summary: Modern graph orchestration library for building stateful, multi-actor applications with LLMs
Home-page: https://github.com/synth-ai/synth-graph
Author: Synth AI
Author-email: Synth AI <team@synth.ai>
License: MIT
Keywords: graph,orchestration,workflow,llm,agents,synth
Requires-Python: >=3.8
Dynamic: author
Dynamic: home-page
Dynamic: requires-python
